dict_viewer/__init__.py
dict_viewer/drint.py
drint-1.0.3.dist-info/LICENSE
drint-1.0.3.dist-info/METADATA
drint-1.0.3.dist-info/WHEEL
drint-1.0.3.dist-info/top_level.txt
drint-1.0.3.dist-info/RECORD
