Metadata-Version: 2.1
Name: drint
Version: 1.0.3
Summary: Providing a complete and beautiful display of dict
Home-page: https://github.com/Domzou-kun/drint
Download-URL: https://github.com/Domzou-kun/drint
Author: Domzou
License: MIT
Keywords: Python python dictionary dict type print pprint
Classifier: Operating System :: Microsoft :: Windows :: Windows 10
Classifier: Programming Language :: Python :: 3.8
Classifier: Programming Language :: Python :: 3.9
Classifier: Programming Language :: Python :: 3.10
Classifier: Topic :: Software Development :: Libraries :: Python Modules
License-File: LICENSE
